lhcb_ftcalib/BSplineCalibration.py
lhcb_ftcalib/CalParameters.py
lhcb_ftcalib/CalibrationFunction.py
lhcb_ftcalib/NSplineCalibration.py
lhcb_ftcalib/PolynomialCalibration.py
lhcb_ftcalib/Tagger.py
lhcb_ftcalib/TaggerCollection.py
lhcb_ftcalib/TaggingData.py
lhcb_ftcalib/__init__.py
lhcb_ftcalib/__main__.py
lhcb_ftcalib/_version.py
lhcb_ftcalib/apply_tagger.py
lhcb_ftcalib/combination.py
lhcb_ftcalib/constants.py
lhcb_ftcalib/ft_types.py
lhcb_ftcalib/link_functions.py
lhcb_ftcalib/plotting.py
lhcb_ftcalib/printing.py
lhcb_ftcalib/resolution_model.py
lhcb_ftcalib/save_calibration.py
lhcb_ftcalib/toy_tagger.py
lhcb_ftcalib/warnings.py
lhcb_ftcalib-1.5.5.dist-info/LICENSE.txt
lhcb_ftcalib-1.5.5.dist-info/METADATA
lhcb_ftcalib-1.5.5.dist-info/WHEEL
lhcb_ftcalib-1.5.5.dist-info/entry_points.txt
lhcb_ftcalib-1.5.5.dist-info/top_level.txt
lhcb_ftcalib-1.5.5.dist-info/RECORD
