Metadata-Version: 2.1
Name: lhcb_ftcalib
Version: 1.5.5
Summary: Library for calibrating flavour tagging algorithms at LHCb
Home-page: https://gitlab.cern.ch/lhcb-ft/lhcb_ftcalib
Author: Vukan Jevtic, Quentin Führing
Author-email: vukan.jevtic@cern.ch
License: GPLv3
Classifier: Programming Language :: Python :: 3
Classifier: Programming Language :: Python :: 3.12
Classifier: License :: OSI Approved :: GNU General Public License v3 (GPLv3)
Classifier: Operating System :: OS Independent
Classifier: Development Status :: 5 - Production/Stable
Classifier: Environment :: Console
Classifier: Intended Audience :: Science/Research
License-File: LICENSE.txt
Requires-Dist: numpy >1.21
Requires-Dist: pandas >2.2.1
Requires-Dist: scipy
Requires-Dist: iminuit >2.3.0
Requires-Dist: matplotlib >=3.3.0
Requires-Dist: numba <=0.61.2
Requires-Dist: uproot !=5.6.7,!=5.6.8,>=5.3.0
Provides-Extra: dev
Requires-Dist: pytest >4 ; extra == 'dev'
Requires-Dist: flake8 ; extra == 'dev'
